sprockets.mixins.sentry-2.0.1-py3.7-nspkg.pth
sprockets/mixins/sentry/__init__.py
sprockets.mixins.sentry-2.0.1.dist-info/LICENSE
sprockets.mixins.sentry-2.0.1.dist-info/METADATA
sprockets.mixins.sentry-2.0.1.dist-info/WHEEL
sprockets.mixins.sentry-2.0.1.dist-info/namespace_packages.txt
sprockets.mixins.sentry-2.0.1.dist-info/top_level.txt
sprockets.mixins.sentry-2.0.1.dist-info/RECORD
