Metadata-Version: 2.1
Name: sprockets.mixins.sentry
Version: 2.0.1
Summary: A RequestHandler mixin for sending exceptions to Sentry
Home-page: https://github.com/sprockets/sprockets.mixins.sentry.git
Author: AWeber Communications
Author-email: api@aweber.com
License: BSD
Platform: UNKNOWN
Classifier: Development Status :: 5 - Production/Stable
Classifier: Intended Audience :: Developers
Classifier: License :: OSI Approved :: BSD License
Classifier: Natural Language :: English
Classifier: Operating System :: OS Independent
Classifier: Programming Language :: Python :: 3
Classifier: Programming Language :: Python :: 3.5
Classifier: Programming Language :: Python :: 3.6
Classifier: Programming Language :: Python :: 3.7
Classifier: Programming Language :: Python :: Implementation :: CPython
Classifier: Topic :: Software Development :: Libraries
Classifier: Topic :: Software Development :: Libraries :: Python Modules
Requires-Python: >=3.5
Requires-Dist: raven (<7,>=6)
Requires-Dist: tornado (<7,>=4)
